wcpan/drive/google/__init__.py
wcpan/drive/google/_api/__init__.py
wcpan/drive/google/_api/changes.py
wcpan/drive/google/_api/files.py
wcpan/drive/google/_hasher.py
wcpan/drive/google/_lib.py
wcpan/drive/google/_network.py
wcpan/drive/google/_oauth.py
wcpan/drive/google/_readable.py
wcpan/drive/google/_service.py
wcpan/drive/google/_writable.py
wcpan/drive/google/exceptions.py
wcpan/drive/google/lib.py
wcpan/drive/google/py.typed
wcpan_drive_google-9.1.7.dist-info/LICENSE.txt
wcpan_drive_google-9.1.7.dist-info/METADATA
wcpan_drive_google-9.1.7.dist-info/WHEEL
wcpan_drive_google-9.1.7.dist-info/RECORD
