Metadata-Version: 2.1
Name: wcpan-drive-google
Version: 9.1.7
Summary: Google Drive driver for wcpan.drive
License: MIT
Author: Wei-Cheng Pan
Author-email: legnaleurc@gmail.com
Requires-Python: >=3.12,<4.0
Classifier: Development Status :: 3 - Alpha
Classifier: Intended Audience :: Developers
Classifier: License :: OSI Approved :: MIT License
Classifier: Operating System :: OS Independent
Classifier: Programming Language :: Python :: 3
Classifier: Programming Language :: Python :: 3.12
Classifier: Topic :: Software Development :: Libraries
Classifier: Typing :: Typed
Requires-Dist: aiohttp (>=3.6.0,<4.0.0)
Requires-Dist: wcpan-drive-core (>=4.1.0,<5.0.0)
